essay_qwen_mcp_server_lc/__init__.py
essay_qwen_mcp_server_lc/server.py
essay_qwen_mcp_server_lc-0.1.4.dist-info/METADATA
essay_qwen_mcp_server_lc-0.1.4.dist-info/WHEEL
essay_qwen_mcp_server_lc-0.1.4.dist-info/entry_points.txt
essay_qwen_mcp_server_lc-0.1.4.dist-info/RECORD
