Metadata-Version: 2.4
Name: essay-qwen-mcp-server-lc
Version: 0.1.4
Summary: Add your description here
Requires-Python: >=3.11
Requires-Dist: mcp[cli,httpx]>=1.9.0
Requires-Dist: openai>=1.78.1
